{
    "Engineer": {
        "Model": "NPCEngineer",
        "Speech": [
            {
                "Check": {
                    "EngineerIntroduced": false,
                    "HasMiscFluxCapacitor": false
                },
                "Flag": "EngineerIntroduced",
                "Text": "Game.Message.EngineerIntro"
            },
            {
                "Check": {
                    "EngineerIntroduced": true,
                    "HasMiscFluxCapacitor": false
                },
                "Text": "Game.Message.EngineerFlux"
            },
            {
                "Check": {
                    "HasMiscFluxCapacitor": true,
                    "PlacedFluxCapacitor": false
                },
                "Flag": "PlacedFluxCapacitor",
                "Text": "Game.Message.EngineerPlace"
            },
            {
                "Check": {
                    "PlacedFluxCapacitor": true
                },
                "Text": "Game.Message.EngineerTip"
            }
        ],
        "Wander": false
    }
}
